{
  "tasks": [
    {
      "description": "Learn React",
      "day": "2022-08-16",
      "hour": "02:10",
      "category": "Personal",
      "id": 1
    },
    {
      "description": "Learn React",
      "day": "2022-08-16",
      "hour": "03:10",
      "category": "Personal",
      "id": 2
    },
    {
      "description": "dasdasd",
      "day": "2022-08-16",
      "hour": "04:10",
      "category": "Work",
      "id": 3
    },
    {
      "description": "412421421",
      "day": "2022-08-14",
      "hour": "01:10",
      "category": "Study",
      "id": 4
    },
    {
      "description": "321312321",
      "day": "2022-08-14",
      "hour": "02:10",
      "category": "Work",
      "id": 5
    },
    {
      "description": "1412412412",
      "day": "2022-08-14",
      "hour": "03:10",
      "category": "Study",
      "id": 6
    },
    {
      "description": "4124214124",
      "day": "2022-08-14",
      "hour": "01:10",
      "category": "Personal",
      "id": 7
    },
    {
      "description": "3213123123",
      "day": "2022-08-15",
      "hour": "02:10",
      "category": "Work",
      "id": 8
    },
    {
      "description": "321312312",
      "day": "2022-08-15",
      "hour": "03:10",
      "category": "Study",
      "id": 9
    },
    {
      "description": "new",
      "day": "2022-08-15",
      "hour": "04:10",
      "category": "Study",
      "id": 10
    },
    {
      "description": "fgsffdsfsdfsd",
      "day": "2022-08-16",
      "hour": "19:50",
      "category": "Study",
      "id": 11
    },
    {
      "description": "<div>123</div>",
      "day": "2022-08-01",
      "hour": "19:19",
      "category": "Work",
      "id": 12
    }
  ]
}